eagers/__init__.py
eagers/basic/__init__.py
eagers/basic/all_demands.py
eagers/basic/auto_set_startdate.py
eagers/basic/best_eff.py
eagers/basic/build_time_vector.py
eagers/basic/check_ac_dc.py
eagers/basic/component_output.py
eagers/basic/constrain_min_max.py
eagers/basic/datetime_ext.py
eagers/basic/file_handling.py
eagers/basic/find_gen_node.py
eagers/basic/gen_limit.py
eagers/basic/get_data.py
eagers/basic/hdf5.py
eagers/basic/interp_numerical.py
eagers/basic/logger.py
eagers/basic/lowess.py
eagers/basic/marginal_cost.py
eagers/basic/messages.py
eagers/basic/net_cost.py
eagers/basic/result_template.py
eagers/basic/solar_calc.py
eagers/basic/ss_response.py
eagers/basic/typical_day.py
eagers/basic/update_component_spec.py
eagers/class_definition/__init__.py
eagers/class_definition/data_constructed.py
eagers/class_definition/data_set.py
eagers/config/__init__.py
eagers/config/dataset.py
eagers/config/doc.py
eagers/config/excel_interface.py
eagers/config/network.py
eagers/config/path_spec.py
eagers/config/plots.py
eagers/config/precision.py
eagers/config/simulation.py
eagers/config/text.py
eagers/config/units.py
eagers/config/user.py
eagers/config/weather_file.py
eagers/demo_files/default_project.xlsx
eagers/demo_files/default_testdata.xlsx
eagers/extras.py
eagers/forecasting/__init__.py
eagers/forecasting/arima.py
eagers/forecasting/arma.py
eagers/forecasting/calculate_fits.py
eagers/forecasting/hydro_forecast.py
eagers/forecasting/input_cost_forecast.py
eagers/forecasting/surface_forecast.py
eagers/forecasting/water_year_forecast.py
eagers/forecasting/weather_forecast.py
eagers/plot/__init__.py
eagers/plot/dispatch_step.py
eagers/read/__init__.py
eagers/read/convert_stream_flows.py
eagers/read/example_file.py
eagers/read/excel_interface.py
eagers/read/excel_interface_project_help.txt
eagers/read/excel_interface_testdata_help.txt
eagers/read/load_dispatch_result.py
eagers/read/read_test_data.py
eagers/read/usace_scrape.py
eagers/read/usgs_web_scrape.py
eagers-0.4.2.dist-info/LICENSE
eagers-0.4.2.dist-info/WHEEL
eagers-0.4.2.dist-info/METADATA
eagers-0.4.2.dist-info/RECORD
