Metadata-Version: 2.1
Name: eagers
Version: 0.4.2
Summary: Efficient Allocation of Grid Energy Resources including Storage
License: MIT
Author: Dustin McLarty
Author-email: dustin.mclarty@wsu.edu
Requires-Python: >=3.6,<4.0
Classifier: License :: OSI Approved :: MIT License
Classifier: Programming Language :: Python :: 3
Classifier: Programming Language :: Python :: 3.10
Classifier: Programming Language :: Python :: 3.6
Classifier: Programming Language :: Python :: 3.7
Classifier: Programming Language :: Python :: 3.8
Classifier: Programming Language :: Python :: 3.9
Provides-Extra: building-plus
Requires-Dist: building-plus (>=0.1.6,<0.2.0); extra == "building-plus"
Requires-Dist: ecos (>=2.0.7,<3.0.0)
Requires-Dist: matplotlib (>=3.1.1,<4.0.0)
Requires-Dist: numpy (>=1.16.4,<2.0.0)
Requires-Dist: openpyxl (>=3.0.3,<4.0.0)
Requires-Dist: scipy (>=1.3.1,<2.0.0)
Requires-Dist: tables (>=3.6.1,<4.0.0)
